testcase/__init__.py
testcase/testcase.py
testcase-0.1.0.dist-info/METADATA
testcase-0.1.0.dist-info/RECORD
testcase-0.1.0.dist-info/WHEEL
testcase-0.1.0.dist-info/top_level.txt
