Metadata-Version: 2.1
Name: testcase
Version: 0.1.0
Summary: Run tabular unit tests
Home-page: https://github.com/ajzaff/testcase
Author: Alan Zaffetti
Author-email: ajzaff@gmail.com
License: UNKNOWN
Project-URL: Bug Reports, https://github.com/ajzaff/testcase/issues
Project-URL: Source, https://github.com/ajzaff/testcase/
Keywords: tabular test development utility
Platform: UNKNOWN
Classifier: Development Status :: 3 - Alpha
Classifier: Intended Audience :: Developers
Classifier: Topic :: Software Development :: Testing :: Unit
Classifier: License :: OSI Approved :: Apache Software License
Classifier: Programming Language :: Python :: 2
Classifier: Programming Language :: Python :: 2.7
Classifier: Programming Language :: Python :: 3
Classifier: Programming Language :: Python :: 3.4
Classifier: Programming Language :: Python :: 3.5
Classifier: Programming Language :: Python :: 3.6
